Fontek.py
fontek-1.1.0.dist-info/METADATA
fontek-1.1.0.dist-info/WHEEL
fontek-1.1.0.dist-info/top_level.txt
fontek-1.1.0.dist-info/RECORD
