Metadata-Version: 2.4
Name: fontek
Version: 1.1.0
Summary: A powerful fonting library for better experience in the field of terminal fonting. It has Rich at it's backend.
Author: Swastik
Requires-Python: >=3.8
